{
    "name": "0.workspace",
    "version": "0.0.1",
    "scripts": {
        "install": "scripts/install.sh",
        "start": ".0/0.CloudIDE.Genesis/scripts/run.sh",
        "clean": ".0/0.CloudIDE.Genesis/scripts/contract.sh"
    },
    "dependencies": {
        "bash.origin": "^0.1.26"
    },
    "description": "0.workspace ===========",
    "_id": "0.workspace@0.0.1",
    "_shasum": "697a8ec6eb9acfa641cb1d5e6477bf4efc5df992",
    "_from": ".",
    "_npmVersion": "1.4.28",
    "_npmUser": {
        "name": "cadorn",
        "email": "christoph@christophdorn.com"
    },
    "maintainers": [
        {
            "name": "cadorn",
            "email": "christoph@christophdorn.com"
        }
    ],
    "dist": {
        "shasum": "697a8ec6eb9acfa641cb1d5e6477bf4efc5df992",
        "tarball": "https://registry.npmjs.org/0.workspace/-/0.workspace-0.0.1.tgz",
        "integrity": "sha512-DWSnxv2Q4Gk3kd302aPu+ouV4xXcSP0zn4ZVksz+Krnk/v2x1jcn1zpKj+hsXz0zTmt5mirDS7SyH01xB4q2fg==",
        "signatures": [
            {
                "keyid": "SHA256:jl3bwswu80PjjokCgh0o2w5c2U4LhQAE57gj9cz1kzA",
                "sig": "MEYCIQDEJ6YZ+zDsA8psEGsk9AJH30lJ8zEMTdqkYPiw/IY9ngIhAN298qopiJwaSU8tfOMjrlrB/ea1z1ZdFRYCQ0L3QZ6a"
            }
        ]
    }
}